airflow_mcp_server/__init__.py
airflow_mcp_server/__main__.py
airflow_mcp_server/config.py
airflow_mcp_server/hierarchical_manager.py
airflow_mcp_server/knowledge_resources.py
airflow_mcp_server/openapi_parser.py
airflow_mcp_server/prompts.py
airflow_mcp_server/resources.py
airflow_mcp_server/server_safe.py
airflow_mcp_server/server_unsafe.py
airflow_mcp_server/toolset.py
airflow_mcp_server/utils/__init__.py
airflow_mcp_server/utils/category_mapper.py
airflow_mcp_server-0.9.1.dist-info/METADATA
airflow_mcp_server-0.9.1.dist-info/WHEEL
airflow_mcp_server-0.9.1.dist-info/entry_points.txt
airflow_mcp_server-0.9.1.dist-info/licenses/LICENSE
airflow_mcp_server-0.9.1.dist-info/RECORD
