Metadata-Version: 2.4
Name: airflow-mcp-server
Version: 0.9.1
Summary: MCP Server for Airflow
Project-URL: GitHub, https://github.com/abhishekbhakat/airflow-mcp-server
Project-URL: Issues, https://github.com/abhishekbhakat/airflow-mcp-server/issues
Author-email: Abhishek Bhakat <abhishek.bhakat@hotmail.com>
License-Expression: MIT
License-File: LICENSE
Classifier: Development Status :: 3 - Alpha
Classifier: Operating System :: OS Independent
Classifier: Programming Language :: Python :: 3.10
Classifier: Programming Language :: Python :: 3.11
Classifier: Programming Language :: Python :: 3.12
Requires-Python: >=3.10
Requires-Dist: aiohttp>=3.9.0
Requires-Dist: click>=8.3.0
Requires-Dist: mcp>=1.16.0
Requires-Dist: pyyaml>=6.0.3
Requires-Dist: starlette>=0.37.0
Requires-Dist: uvicorn>=0.30.0
Provides-Extra: dev
Requires-Dist: build>=1.2.2.post1; extra == 'dev'
Requires-Dist: pre-commit>=4.2.0; extra == 'dev'
Requires-Dist: pytest-asyncio>=1.0.0; extra == 'dev'
Requires-Dist: pytest-mock>=3.14.1; extra == 'dev'
Requires-Dist: pytest>=8.3.5; extra == 'dev'
Requires-Dist: ruff>=0.11.12; extra == 'dev'
